pisht30/__init__.py
pisht30/pisht30.py
pisht30-1.0.0.dist-info/DESCRIPTION.rst
pisht30-1.0.0.dist-info/METADATA
pisht30-1.0.0.dist-info/RECORD
pisht30-1.0.0.dist-info/WHEEL
pisht30-1.0.0.dist-info/metadata.json
pisht30-1.0.0.dist-info/top_level.txt
