Metadata-Version: 2.0
Name: pisht30
Version: 1.0.0
Summary: To use SHT30 with pigpio
Home-page: https://github.com/Langur/pisht30
Author: Akihisa ONODA
Author-email: akihisa.onoda@osarusystem.com
License: MIT
Keywords: pisht30 sht30 sht31 sht35 env2hat env3hat pigpio temperature humidity sensor i2c
Platform: UNKNOWN
Classifier: License :: OSI Approved :: MIT License
Classifier: Programming Language :: Python :: 3
Classifier: Programming Language :: Python :: 3.7
Requires-Dist: pigpio
